repomap/__init__.py
repomap/__main__.py
repomap/cache.py
repomap/cli.py
repomap/core.py
repomap/graph.py
repomap/ranking.py
repomap/tags.py
repomap/tree.py
repomap/utils.py
repomap/queries/tree-sitter-language-pack/README.md
repomap/queries/tree-sitter-language-pack/arduino-tags.scm
repomap/queries/tree-sitter-language-pack/c-tags.scm
repomap/queries/tree-sitter-language-pack/chatito-tags.scm
repomap/queries/tree-sitter-language-pack/clojure-tags.scm
repomap/queries/tree-sitter-language-pack/commonlisp-tags.scm
repomap/queries/tree-sitter-language-pack/cpp-tags.scm
repomap/queries/tree-sitter-language-pack/csharp-tags.scm
repomap/queries/tree-sitter-language-pack/d-tags.scm
repomap/queries/tree-sitter-language-pack/dart-tags.scm
repomap/queries/tree-sitter-language-pack/elisp-tags.scm
repomap/queries/tree-sitter-language-pack/elixir-tags.scm
repomap/queries/tree-sitter-language-pack/elm-tags.scm
repomap/queries/tree-sitter-language-pack/gleam-tags.scm
repomap/queries/tree-sitter-language-pack/go-tags.scm
repomap/queries/tree-sitter-language-pack/java-tags.scm
repomap/queries/tree-sitter-language-pack/javascript-tags.scm
repomap/queries/tree-sitter-language-pack/lua-tags.scm
repomap/queries/tree-sitter-language-pack/matlab-tags.scm
repomap/queries/tree-sitter-language-pack/ocaml-tags.scm
repomap/queries/tree-sitter-language-pack/ocaml_interface-tags.scm
repomap/queries/tree-sitter-language-pack/pony-tags.scm
repomap/queries/tree-sitter-language-pack/properties-tags.scm
repomap/queries/tree-sitter-language-pack/python-tags.scm
repomap/queries/tree-sitter-language-pack/r-tags.scm
repomap/queries/tree-sitter-language-pack/racket-tags.scm
repomap/queries/tree-sitter-language-pack/ruby-tags.scm
repomap/queries/tree-sitter-language-pack/rust-tags.scm
repomap/queries/tree-sitter-language-pack/solidity-tags.scm
repomap/queries/tree-sitter-language-pack/swift-tags.scm
repomap/queries/tree-sitter-language-pack/udev-tags.scm
pyrepomap-0.1.4.dist-info/METADATA
pyrepomap-0.1.4.dist-info/WHEEL
pyrepomap-0.1.4.dist-info/entry_points.txt
pyrepomap-0.1.4.dist-info/licenses/LICENSE
pyrepomap-0.1.4.dist-info/licenses/NOTICE
pyrepomap-0.1.4.dist-info/RECORD
