Metadata-Version: 2.4
Name: pyrepomap
Version: 0.1.4
Summary: Tree-sitter based repository map generator - extract and visualize code structure
Project-URL: Homepage, https://github.com/cdpath/repomap
Project-URL: Repository, https://github.com/cdpath/repomap
License: Apache-2.0
License-File: LICENSE
License-File: NOTICE
Keywords: ast,code-analysis,code-structure,repository-map,tree-sitter
Classifier: Development Status :: 4 - Beta
Classifier: Environment :: Console
Classifier: Intended Audience :: Developers
Classifier: License :: OSI Approved :: Apache Software License
Classifier: Programming Language :: Python :: 3
Classifier: Programming Language :: Python :: 3.10
Classifier: Programming Language :: Python :: 3.11
Classifier: Programming Language :: Python :: 3.12
Classifier: Programming Language :: Python :: 3.13
Classifier: Topic :: Software Development
Classifier: Topic :: Software Development :: Code Generators
Requires-Python: >=3.10
Requires-Dist: diskcache>=5.6.3
Requires-Dist: grep-ast>=0.9.0
Requires-Dist: matplotlib>=3.10.8
Requires-Dist: networkx>=3.0
Requires-Dist: numpy>=1.26
Requires-Dist: pydot>=4.0.1
Requires-Dist: pygments>=2.0
Requires-Dist: scipy>=1.10
Requires-Dist: tqdm>=4.0
Requires-Dist: tree-sitter-language-pack>=0.11.0
